odoo/addons/sale_order_digitized_signature/README.rst
odoo/addons/sale_order_digitized_signature/__init__.py
odoo/addons/sale_order_digitized_signature/__manifest__.py
odoo/addons/sale_order_digitized_signature/i18n/es.po
odoo/addons/sale_order_digitized_signature/i18n/it.po
odoo/addons/sale_order_digitized_signature/i18n/sale_order_digitized_signature.pot
odoo/addons/sale_order_digitized_signature/i18n/zh_CN.po
odoo/addons/sale_order_digitized_signature/migrations/13.0.1.0.0/post-migration.py
odoo/addons/sale_order_digitized_signature/migrations/13.0.1.0.0/pre-migration.py
odoo/addons/sale_order_digitized_signature/models/__init__.py
odoo/addons/sale_order_digitized_signature/models/sale.py
odoo/addons/sale_order_digitized_signature/readme/CONTRIBUTORS.rst
odoo/addons/sale_order_digitized_signature/readme/DESCRIPTION.rst
odoo/addons/sale_order_digitized_signature/readme/INSTALL.rst
odoo/addons/sale_order_digitized_signature/readme/USAGE.rst
odoo/addons/sale_order_digitized_signature/report/report_saleorder.xml
odoo/addons/sale_order_digitized_signature/static/description/icon.png
odoo/addons/sale_order_digitized_signature/static/description/index.html
odoo/addons/sale_order_digitized_signature/views/sale_views.xml
odoo14_addon_sale_order_digitized_signature-14.0.1.0.1.dev9.dist-info/METADATA
odoo14_addon_sale_order_digitized_signature-14.0.1.0.1.dev9.dist-info/WHEEL
odoo14_addon_sale_order_digitized_signature-14.0.1.0.1.dev9.dist-info/top_level.txt
odoo14_addon_sale_order_digitized_signature-14.0.1.0.1.dev9.dist-info/RECORD
