Metadata-Version: 2.1
Name: odoo14-addon-sale_order_digitized_signature
Version: 14.0.1.0.1.dev9
Summary: Capture customer signature on the sales order
Home-page: https://github.com/OCA/sale-workflow
Author: Tecnativa, Odoo Community Association (OCA)
Author-email: support@odoo-community.org
License: AGPL-3
Classifier: Programming Language :: Python
Classifier: Framework :: Odoo
Classifier: Framework :: Odoo :: 14.0
Classifier: License :: OSI Approved :: GNU Affero General Public License v3
Classifier: Development Status :: 5 - Production/Stable
Requires-Python: >=3.6
Requires-Dist: odoo<14.1dev,>=14.0a
